Workbook

Sheet Dashboard
B2: TECH FUNDAMENTALS | I2: 2021 → 2025
B3: VS. STOCK PERFORMANCE | I3: 5 MEGA-CAPS
B4: Historical market & financial-statement data processed in Python · 2021–2025 analysis period
B7: AVG RETURN | D7: AVG VOLATILITY | E7: AVG SHARPE | G7: AVG REVENUE CAGR | I7: AVG OP. MARGIN
B8: =AVERAGE(E15:E19) -> 0.285481 | D8: =AVERAGE(F15:F19) -> 0.3441062 | E8: =AVERAGE(G15:G19) -> 0.6734074 | G8: =AVERAGE(H15:H19) -> 0.2844492 | I8: =AVERAGE(I15:I19) -> 0.3646424
B9: ="▲ BEST "&INDEX($B$15:$B$19,MATCH(MAX(E15:E19),E15:E19,0))&" · "&FIXED(MAX(E15:E19)*100,1)&"%" -> ▲ BEST NVDA · 70,4% | D9: ="▼ LOWEST "&INDEX($B$15:$B$19,MATCH(MIN(F15:F19),F15:F19,0))&" · "&FIXED(MIN(F15:F19)*100,1)&"%" -> ▼ LOWEST MSFT · 25,7% | E9: ="▲ BEST "&INDEX($B$15:$B$19,MATCH(MAX(G15:G19),G15:G19,0))&" · "&FIXED(MAX(G15:G19),2) -> ▲ BEST NVDA · 1,29 | G9: ="▲ BEST "&INDEX($B$15:$B$19,MATCH(MAX(H15:H19),H15:H19,0))&" · "&FIXED(MAX(H15:H19)*100,1)&"%" -> ▲ BEST NVDA · 100,0% | I9: ="▲ BEST "&INDEX($B$15:$B$19,MATCH(MAX(I15:I19),I15:I19,0))&" · "&FIXED(MAX(I15:I19)*100,1)&"%" -> ▲ BEST NVDA · 60,4%
B11: FOCUS ▸ | C11: AMZN | D11: ← pick a ticker | E11: RANK BY ▸ | F11: Annualized Return | H11: ← every chart & rank reacts
B13: ▌ SCOREBOARD | J13: ="highlighted row = focus · rank recalculates on "&UPPER(F11) -> highlighted row = focus · rank recalculates on ANNUALIZED RETURN
B14: ='Company Data'!A1 -> Ticker | C14: ='Company Data'!B1 -> Company | D14: ='Company Data'!C1 -> Sector | E14: ='Company Data'!D1 -> Annualized Return | F14: ='Company Data'!E1 -> Annualized Volatility | G14: ='Company Data'!F1 -> Sharpe Ratio | H14: ='Company Data'!G1 -> Revenue CAGR | I14: ='Company Data'!H1 -> Operating Margin | J14: Rank
B15: ='Company Data'!A2 -> AAPL | C15: ='Company Data'!B2 -> Apple | D15: ='Company Data'!C2 -> Technology | E15: ='Company Data'!D2 -> 0.166725 | F15: ='Company Data'!E2 -> 0.278626 | G15: ='Company Data'!F2 -> 0.49071 | H15: ='Company Data'!G2 -> 0.018125 | I15: ='Company Data'!H2 -> 0.319708 | J15: {=RANK(INDEX(E15:I15,'Chart Engine'!$B$5),INDEX($E$15:$I$19,0,'Chart Engine'!$B$5),'Chart Engine'!$B$6)} -> 4
B16: ='Company Data'!A3 -> AMZN | C16: ='Company Data'!B3 -> Amazon | D16: ='Company Data'!C3 -> Consumer / Cloud | E16: ='Company Data'!D3 -> 0.077133 | F16: ='Company Data'!E3 -> 0.35106 | G16: ='Company Data'!F3 -> 0.13426 | H16: ='Company Data'!G3 -> 0.117313 | I16: ='Company Data'!H3 -> 0.111553 | J16: {=RANK(INDEX(E16:I16,'Chart Engine'!$B$5),INDEX($E$15:$I$19,0,'Chart Engine'!$B$5),'Chart Engine'!$B$6)} -> 5
B17: ='Company Data'!A4 -> GOOGL | C17: ='Company Data'!B4 -> Alphabet | D17: ='Company Data'!C4 -> Digital Advertising / Cloud | E17: ='Company Data'!D4 -> 0.296631 | F17: ='Company Data'!E4 -> 0.311455 | G17: ='Company Data'!F4 -> 0.856082 | H17: ='Company Data'!G4 -> 0.125117 | I17: ='Company Data'!H4 -> 0.320326 | J17: {=RANK(INDEX(E17:I17,'Chart Engine'!$B$5),INDEX($E$15:$I$19,0,'Chart Engine'!$B$5),'Chart Engine'!$B$6)} -> 2
B18: ='Company Data'!A5 -> MSFT | C18: ='Company Data'!B5 -> Microsoft | D18: ='Company Data'!C5 -> Technology | E18: ='Company Data'!D5 -> 0.183289 | F18: ='Company Data'!E5 -> 0.257143 | G18: ='Company Data'!F5 -> 0.596122 | H18: ='Company Data'!G5 -> 0.16124 | I18: ='Company Data'!H5 -> 0.467808 | J18: {=RANK(INDEX(E18:I18,'Chart Engine'!$B$5),INDEX($E$15:$I$19,0,'Chart Engine'!$B$5),'Chart Engine'!$B$6)} -> 3
B19: ='Company Data'!A6 -> NVDA | C19: ='Company Data'!B6 -> Nvidia | D19: ='Company Data'!C6 -> Semiconductors | E19: ='Company Data'!D6 -> 0.703627 | F19: ='Company Data'!E6 -> 0.522247 | G19: ='Company Data'!F6 -> 1.289863 | H19: ='Company Data'!G6 -> 1.000451 | I19: ='Company Data'!H6 -> 0.603817 | J19: {=RANK(INDEX(E19:I19,'Chart Engine'!$B$5),INDEX($E$15:$I$19,0,'Chart Engine'!$B$5),'Chart Engine'!$B$6)} -> 1
B21: ▌ RISK / RETURN MAP | F21: ="▌ LEADERBOARD · "&UPPER(F11) -> ▌ LEADERBOARD · ANNUALIZED RETURN
B40: ="▌ FOCUS DNA · "&C11&" vs UNIVERSE AVG" -> ▌ FOCUS DNA · AMZN vs UNIVERSE AVG | F40: ▌ DOES REVENUE GROWTH = STOCK RETURN?

Sheet Company Data
A1: Ticker | B1: Company | C1: Sector | D1: Annualized Return | E1: Annualized Volatility | F1: Sharpe Ratio | G1: Revenue CAGR | H1: Operating Margin
A2: AAPL | B2: Apple | C2: Technology | D2: 0.166725 | E2: 0.278626 | F2: 0.49071 | G2: 0.018125 | H2: 0.319708
A3: AMZN | B3: Amazon | C3: Consumer / Cloud | D3: 0.077133 | E3: 0.35106 | F3: 0.13426 | G3: 0.117313 | H3: 0.111553
A4: GOOGL | B4: Alphabet | C4: Digital Advertising / Cloud | D4: 0.296631 | E4: 0.311455 | F4: 0.856082 | G4: 0.125117 | H4: 0.320326
A5: MSFT | B5: Microsoft | C5: Technology | D5: 0.183289 | E5: 0.257143 | F5: 0.596122 | G5: 0.16124 | H5: 0.467808
A6: NVDA | B6: Nvidia | C6: Semiconductors | D6: 0.703627 | E6: 0.522247 | F6: 1.289863 | G6: 1.000451 | H6: 0.603817
A8: Light-blue = hardcoded inputs from the Python pipeline. Edit here → Dashboard updates.

Sheet Notes
A1: PROJECT NOTES
A3: Topic | B3: Meaning
A4: Light-blue numbers | B4: Hardcoded inputs on Company Data that can be replaced
A5: Dashboard selectors | B5: FOCUS (C11) and RANK BY (F11) dropdowns drive the table highlight, ranks and all charts
A6: Annualized return | B6: Compound annual growth of the share price over the sample
A7: Volatility | B7: Standard deviation of daily returns × √252
A8: Sharpe ratio | B8: Excess annual return divided by annualized volatility
A9: Revenue CAGR | B9: Compound annual growth rate of revenue
A10: Operating margin | B10: Operating income divided by revenue
A12: Data status | B12: Real results generated by the executed Python pipeline in analysis_notebook.ipynb
A13: Market data | B13: Historical adjusted share-price data downloaded through yfinance
A14: Fundamentals | B14: Annual revenue and operating income downloaded through yfinance financial statements
A15: Analysis period | B15: 2021–2025
A16: Companies | B16: Apple, Amazon, Alphabet, Microsoft, Nvidia

Sheet Chart Engine
A1: CHART ENGINE
A2: Helper calcs feeding the Dashboard charts & selectors — driven by Dashboard!C11 and Dashboard!F11
A4: Selected metric | B4: =Dashboard!F11 -> Annualized Return
A5: Metric column # | B5: =MATCH(B4,$A$10:$A$14,0) -> 1
A6: Rank order (0 = high→low, 1 = low→high) | B6: {=INDEX($C$10:$C$14,B5)} -> 0
A7: Focus ticker | B7: =Dashboard!C11 -> AMZN
A9: Metric | B9: Higher is better? | C9: RANK order
A10: Annualized Return | B10: Yes | C10: 0
A11: Annualized Volatility | B11: No | C11: 1
A12: Sharpe Ratio | B12: Yes | C12: 0
A13: Revenue CAGR | B13: Yes | C13: 0
A14: Operating Margin | B14: Yes | C14: 0
A17: RANKING — sorted by selected metric (feeds Ranking chart)
A18: Pos | B18: Ticker | C18: Value | D18: Others (%) | E18: Focus (%) | F18: Others (x) | G18: Focus (x)
A19: 1 | B19: =INDEX('Company Data'!$A$2:$A$6,MATCH(C19,INDEX('Company Data'!$D$2:$H$6,0,$B$5),0)) -> NVDA | C19: =IF($B$6=0,LARGE(INDEX('Company Data'!$D$2:$H$6,0,$B$5),A19),SMALL(INDEX('Company Data'!$D$2:$H$6,0,$B$5),A19)) -> 0.703627 | D19: =IF(OR($B$4="Sharpe Ratio",B19=$B$7),NA(),C19) -> 0.703627 | E19: =IF(AND($B$4<>"Sharpe Ratio",B19=$B$7),C19,NA()) -> #N/A | F19: =IF(AND($B$4="Sharpe Ratio",B19<>$B$7),ROUND(C19,2),NA()) -> #N/A | G19: =IF(AND($B$4="Sharpe Ratio",B19=$B$7),ROUND(C19,2),NA()) -> #N/A
A20: 2 | B20: =INDEX('Company Data'!$A$2:$A$6,MATCH(C20,INDEX('Company Data'!$D$2:$H$6,0,$B$5),0)) -> GOOGL | C20: =IF($B$6=0,LARGE(INDEX('Company Data'!$D$2:$H$6,0,$B$5),A20),SMALL(INDEX('Company Data'!$D$2:$H$6,0,$B$5),A20)) -> 0.296631 | D20: =IF(OR($B$4="Sharpe Ratio",B20=$B$7),NA(),C20) -> 0.296631 | E20: =IF(AND($B$4<>"Sharpe Ratio",B20=$B$7),C20,NA()) -> #N/A | F20: =IF(AND($B$4="Sharpe Ratio",B20<>$B$7),ROUND(C20,2),NA()) -> #N/A | G20: =IF(AND($B$4="Sharpe Ratio",B20=$B$7),ROUND(C20,2),NA()) -> #N/A
A21: 3 | B21: =INDEX('Company Data'!$A$2:$A$6,MATCH(C21,INDEX('Company Data'!$D$2:$H$6,0,$B$5),0)) -> MSFT | C21: =IF($B$6=0,LARGE(INDEX('Company Data'!$D$2:$H$6,0,$B$5),A21),SMALL(INDEX('Company Data'!$D$2:$H$6,0,$B$5),A21)) -> 0.183289 | D21: =IF(OR($B$4="Sharpe Ratio",B21=$B$7),NA(),C21) -> 0.183289 | E21: =IF(AND($B$4<>"Sharpe Ratio",B21=$B$7),C21,NA()) -> #N/A | F21: =IF(AND($B$4="Sharpe Ratio",B21<>$B$7),ROUND(C21,2),NA()) -> #N/A | G21: =IF(AND($B$4="Sharpe Ratio",B21=$B$7),ROUND(C21,2),NA()) -> #N/A
A22: 4 | B22: =INDEX('Company Data'!$A$2:$A$6,MATCH(C22,INDEX('Company Data'!$D$2:$H$6,0,$B$5),0)) -> AAPL | C22: =IF($B$6=0,LARGE(INDEX('Company Data'!$D$2:$H$6,0,$B$5),A22),SMALL(INDEX('Company Data'!$D$2:$H$6,0,$B$5),A22)) -> 0.166725 | D22: =IF(OR($B$4="Sharpe Ratio",B22=$B$7),NA(),C22) -> 0.166725 | E22: =IF(AND($B$4<>"Sharpe Ratio",B22=$B$7),C22,NA()) -> #N/A | F22: =IF(AND($B$4="Sharpe Ratio",B22<>$B$7),ROUND(C22,2),NA()) -> #N/A | G22: =IF(AND($B$4="Sharpe Ratio",B22=$B$7),ROUND(C22,2),NA()) -> #N/A
A23: 5 | B23: =INDEX('Company Data'!$A$2:$A$6,MATCH(C23,INDEX('Company Data'!$D$2:$H$6,0,$B$5),0)) -> AMZN | C23: =IF($B$6=0,LARGE(INDEX('Company Data'!$D$2:$H$6,0,$B$5),A23),SMALL(INDEX('Company Data'!$D$2:$H$6,0,$B$5),A23)) -> 0.077133 | D23: =IF(OR($B$4="Sharpe Ratio",B23=$B$7),NA(),C23) -> #N/A | E23: =IF(AND($B$4<>"Sharpe Ratio",B23=$B$7),C23,NA()) -> 0.077133 | F23: =IF(AND($B$4="Sharpe Ratio",B23<>$B$7),ROUND(C23,2),NA()) -> #N/A | G23: =IF(AND($B$4="Sharpe Ratio",B23=$B$7),ROUND(C23,2),NA()) -> #N/A
A26: FOCUS POINT (Risk/Return map) | B26: Volatility | C26: Return
A27: =B7 -> AMZN | B27: =INDEX('Company Data'!$E$2:$E$6,MATCH($B$7,'Company Data'!$A$2:$A$6,0)) -> 0.35106 | C27: =INDEX('Company Data'!$D$2:$D$6,MATCH($B$7,'Company Data'!$A$2:$A$6,0)) -> 0.077133
A30: FOCUS PROFILE — scores vs best-in-universe (1.0 = best)
A31: Metric | B31: Focus raw | C31: Universe avg raw | D31: Best in universe | E31: Focus score | F31: Universe avg score | G31: Label
A32: Annualized Return | B32: =INDEX('Company Data'!$D$2:$H$6,MATCH($B$7,'Company Data'!$A$2:$A$6,0),MATCH($A32,'Company Data'!$D$1:$H$1,0)) -> 0.077133 | C32: =AVERAGE(INDEX('Company Data'!$D$2:$H$6,0,MATCH($A32,'Company Data'!$D$1:$H$1,0))) -> 0.285481 | D32: =IF(INDEX($B$10:$B$14,MATCH($A32,$A$10:$A$14,0))="Yes",MAX(INDEX('Company Data'!$D$2:$H$6,0,MATCH($A32,'Company Data'!$D$1:$H$1,0))),MIN(INDEX('Company Data'!$D$2:$H$6,0,MATCH($A32,'Company Data'!$D$1:$H$1,0)))) -> 0.703627 | E32: =IF(INDEX($B$10:$B$14,MATCH($A32,$A$10:$A$14,0))="Yes",B32/D32,D32/B32) -> 0.109622 | F32: =IF(INDEX($B$10:$B$14,MATCH($A32,$A$10:$A$14,0))="Yes",C32/D32,D32/C32) -> 0.40572775 | G32: Return
A33: Annualized Volatility | B33: =INDEX('Company Data'!$D$2:$H$6,MATCH($B$7,'Company Data'!$A$2:$A$6,0),MATCH($A33,'Company Data'!$D$1:$H$1,0)) -> 0.35106 | C33: =AVERAGE(INDEX('Company Data'!$D$2:$H$6,0,MATCH($A33,'Company Data'!$D$1:$H$1,0))) -> 0.3441062 | D33: =IF(INDEX($B$10:$B$14,MATCH($A33,$A$10:$A$14,0))="Yes",MAX(INDEX('Company Data'!$D$2:$H$6,0,MATCH($A33,'Company Data'!$D$1:$H$1,0))),MIN(INDEX('Company Data'!$D$2:$H$6,0,MATCH($A33,'Company Data'!$D$1:$H$1,0)))) -> 0.257143 | E33: =IF(INDEX($B$10:$B$14,MATCH($A33,$A$10:$A$14,0))="Yes",B33/D33,D33/B33) -> 0.73247593 | F33: =IF(INDEX($B$10:$B$14,MATCH($A33,$A$10:$A$14,0))="Yes",C33/D33,D33/C33) -> 0.74727802 | G33: Low Volatility
A34: Sharpe Ratio | B34: =INDEX('Company Data'!$D$2:$H$6,MATCH($B$7,'Company Data'!$A$2:$A$6,0),MATCH($A34,'Company Data'!$D$1:$H$1,0)) -> 0.13426 | C34: =AVERAGE(INDEX('Company Data'!$D$2:$H$6,0,MATCH($A34,'Company Data'!$D$1:$H$1,0))) -> 0.6734074 | D34: =IF(INDEX($B$10:$B$14,MATCH($A34,$A$10:$A$14,0))="Yes",MAX(INDEX('Company Data'!$D$2:$H$6,0,MATCH($A34,'Company Data'!$D$1:$H$1,0))),MIN(INDEX('Company Data'!$D$2:$H$6,0,MATCH($A34,'Company Data'!$D$1:$H$1,0)))) -> 1.289863 | E34: =IF(INDEX($B$10:$B$14,MATCH($A34,$A$10:$A$14,0))="Yes",B34/D34,D34/B34) -> 0.10408857 | F34: =IF(INDEX($B$10:$B$14,MATCH($A34,$A$10:$A$14,0))="Yes",C34/D34,D34/C34) -> 0.52207669 | G34: Sharpe
A35: Revenue CAGR | B35: =INDEX('Company Data'!$D$2:$H$6,MATCH($B$7,'Company Data'!$A$2:$A$6,0),MATCH($A35,'Company Data'!$D$1:$H$1,0)) -> 0.117313 | C35: =AVERAGE(INDEX('Company Data'!$D$2:$H$6,0,MATCH($A35,'Company Data'!$D$1:$H$1,0))) -> 0.2844492 | D35: =IF(INDEX($B$10:$B$14,MATCH($A35,$A$10:$A$14,0))="Yes",MAX(INDEX('Company Data'!$D$2:$H$6,0,MATCH($A35,'Company Data'!$D$1:$H$1,0))),MIN(INDEX('Company Data'!$D$2:$H$6,0,MATCH($A35,'Company Data'!$D$1:$H$1,0)))) -> 1.000451 | E35: =IF(INDEX($B$10:$B$14,MATCH($A35,$A$10:$A$14,0))="Yes",B35/D35,D35/B35) -> 0.11726012 | F35: =IF(INDEX($B$10:$B$14,MATCH($A35,$A$10:$A$14,0))="Yes",C35/D35,D35/C35) -> 0.28432097 | G35: Revenue Growth
A36: Operating Margin | B36: =INDEX('Company Data'!$D$2:$H$6,MATCH($B$7,'Company Data'!$A$2:$A$6,0),MATCH($A36,'Company Data'!$D$1:$H$1,0)) -> 0.111553 | C36: =AVERAGE(INDEX('Company Data'!$D$2:$H$6,0,MATCH($A36,'Company Data'!$D$1:$H$1,0))) -> 0.3646424 | D36: =IF(INDEX($B$10:$B$14,MATCH($A36,$A$10:$A$14,0))="Yes",MAX(INDEX('Company Data'!$D$2:$H$6,0,MATCH($A36,'Company Data'!$D$1:$H$1,0))),MIN(INDEX('Company Data'!$D$2:$H$6,0,MATCH($A36,'Company Data'!$D$1:$H$1,0)))) -> 0.603817 | E36: =IF(INDEX($B$10:$B$14,MATCH($A36,$A$10:$A$14,0))="Yes",B36/D36,D36/B36) -> 0.18474637 | F36: =IF(INDEX($B$10:$B$14,MATCH($A36,$A$10:$A$14,0))="Yes",C36/D36,D36/C36) -> 0.60389555 | G36: Op. Margin
